{
  "db_name": "PostgreSQL",
  "query": "\n            INSERT INTO knowledge_base_articles (title, content, author_id, published)\n            VALUES ($1, $2, $3, $4)\n            RETURNING *\n            ",
  "describe": {
    "columns": [
      {
        "ordinal": 0,
        "name": "id",
        "type_info": "Int4"
      },
      {
        "ordinal": 1,
        "name": "title",
        "type_info": "Varchar"
      },
      {
        "ordinal": 2,
        "name": "content",
        "type_info": "Text"
      },
      {
        "ordinal": 3,
        "name": "author_id",
        "type_info": "Int4"
      },
      {
        "ordinal": 4,
        "name": "published",
        "type_info": "Bool"
      },
      {
        "ordinal": 5,
        "name": "created_at",
        "type_info": "Timestamptz"
      },
      {
        "ordinal": 6,
        "name": "updated_at",
        "type_info": "Timestamptz"
      }
    ],
    "parameters": {
      "Left": [
        "Varchar",
        "Text",
        "Int4",
        "Bool"
      ]
    },
    "nullable": [
      false,
      false,
      false,
      false,
      false,
      true,
      true
    ]
  },
  "hash": "31bbc4d3b7ba37e7ec0d30f2bfa79f7c8901a87c7c93bc6ce6f3b8ec9a73388d"
}
